crowns/__init__.py
crowns/the.proc.py
crowns/_status/__init__.py
crowns/_status/status.proc.py
crowns/_status/monitors/mint_2_trend_2_mint/monitor_1.py
crowns/_status/monitors_process/1/monitor_1.py
crowns/climate/__init__.py
crowns/clique/__init__.py
crowns/clique/group/trends.py
crowns/config/scan.py
crowns/config/sculpt.py
crowns/mints/clique.py
crowns/mints/names.py
crowns/modules/freight--/save.py
crowns/modules/moves/mint_to_trends.py
crowns/modules/moves/trends_to_mint.py
crowns/modules/moves/save/__init__.py
crowns/modules/moves/save/modules/zip_and_save_to_gridfs.py
crowns/modules/moves/trends/extract_to_temp.py
crowns/modules/moves/trends/find.py
crowns/modules/moves/trends/forget.py
crowns/modules/moves/trends/off.py
crowns/modules/moves/trends/on.py
crowns/modules/moves/trends/show.py
crowns/modules/moves/trends/zips/forget.py
crowns/treasuries/close.py
crowns/treasuries/create.py
crowns/treasuries/destroy.py
crowns/treasuries/names.py
crowns/treasuries/open.py
crowns/treasuries/path.py
crowns/treasuries/search.py
crowns/treasuries/clique/__init__.py
crowns-2.0.0.dist-info/METADATA
crowns-2.0.0.dist-info/WHEEL
crowns-2.0.0.dist-info/entry_points.txt
crowns-2.0.0.dist-info/top_level.txt
crowns-2.0.0.dist-info/RECORD
