Metadata-Version: 2.1
Name: crowns
Version: 2.0.0
Summary: How to organize a throne room.
Keywords: leads,organization
Requires-Dist: volts
Requires-Dist: ships
Requires-Dist: somatic
Requires-Dist: law-dictionary
Requires-Dist: rich
Requires-Dist: tinydb
Requires-Dist: click
